luna_quantum-1.1.3.dist-info/METADATA
luna_quantum-1.1.3.dist-info/WHEEL
luna_quantum-1.1.3.dist-info/licenses/LICENSE
luna_quantum-1.1.3.dist-info/licenses/NOTICE
luna_quantum/__init__.py
luna_quantum/__init__.pyi
luna_quantum/_core.cpython-312-x86_64-linux-gnu.so
luna_quantum/_core.pyi
luna_quantum/_utility.py
luna_quantum/_utility.pyi
luna_quantum/algorithms/__init__.py
luna_quantum/aqm_overwrites/__init__.py
luna_quantum/aqm_overwrites/model.py
luna_quantum/backends/__init__.py
luna_quantum/client/__init__.py
luna_quantum/client/controllers/__init__.py
luna_quantum/client/controllers/luna_http_client.py
luna_quantum/client/controllers/luna_platform_client.py
luna_quantum/client/controllers/luna_q.py
luna_quantum/client/controllers/luna_solve.py
luna_quantum/client/error/__init__.py
luna_quantum/client/error/luna_api_key_invalid_error.py
luna_quantum/client/error/luna_api_key_missing_error.py
luna_quantum/client/error/luna_error.py
luna_quantum/client/error/luna_server_error.py
luna_quantum/client/error/timeout_error.py
luna_quantum/client/error/transformation_error.py
luna_quantum/client/error/utils/__init__.py
luna_quantum/client/error/utils/http_error_utils.py
luna_quantum/client/interfaces/__init__.py
luna_quantum/client/interfaces/clients/__init__.py
luna_quantum/client/interfaces/clients/circuit_rest_client_i.py
luna_quantum/client/interfaces/clients/info_rest_client_i.py
luna_quantum/client/interfaces/clients/model_rest_client_i.py
luna_quantum/client/interfaces/clients/qpu_token_rest_client_i.py
luna_quantum/client/interfaces/clients/rest_client_i.py
luna_quantum/client/interfaces/clients/solve_job_rest_client_i.py
luna_quantum/client/interfaces/clients/users_rest_client_i.py
luna_quantum/client/interfaces/services/__init__.py
luna_quantum/client/interfaces/services/luna_q_i.py
luna_quantum/client/interfaces/services/luna_solve_i.py
luna_quantum/client/interfaces/services/service_i.py
luna_quantum/client/rest_client/__init__.py
luna_quantum/client/rest_client/circuit_rest_client.py
luna_quantum/client/rest_client/info_rest_client.py
luna_quantum/client/rest_client/model_rest_client.py
luna_quantum-1.1.3.dist-info/RECORD
